consoleAI/ModelAI.py
consoleAI/__init__.py
vuxnx-0.1.0.dist-info/METADATA
vuxnx-0.1.0.dist-info/WHEEL
vuxnx-0.1.0.dist-info/top_level.txt
vuxnx-0.1.0.dist-info/RECORD
