Metadata-Version: 2.1
Name: vuxnx
Version: 0.1.0
Summary: A simple AI console package
Author: Vuxnx
Author-email: trongnghiavu649@gmail.com
Classifier: Programming Language :: Python :: 3
Classifier: License :: OSI Approved :: MIT License
Classifier: Operating System :: OS Independent
Requires-Python: >=3.6
